{
    "core": {
        "magic": "APF_VER_1",
        "metadata": {
            "platform_ids": [
                "openfpgaos"
            ],
            "shortname": "openfpgaOS",
            "description": "openfpgaOS on VexiiRiscv RISC-V CPU",
            "author": "ThinkElastic",
            "url": "",
            "version": "0.7",
            "date_release": "2026-06-17"
        },
        "framework": {
            "target_product": "Analogue Pocket",
            "version_required": "2.2",
            "sleep_supported": false,
            "dock": {
                "supported": true,
                "analog_output": false
            },
            "hardware": {
                "link_port": true,
                "cartridge_adapter": 0
            }
        },
        "cores": [
            {
                "name": "os25",
                "id": 0,
                "filename": "os25.rbf_r",
                "chip32_vm": "loader.bin"
            },
            {
                "name": "os30",
                "id": 1,
                "filename": "os30.rbf_r",
                "chip32_vm": "loader.bin"
            }
        ]
    }
}
